stactools/sentinel1/__init__.py
stactools/sentinel1/bands.py
stactools/sentinel1/commands.py
stactools/sentinel1/constants.py
stactools/sentinel1/formats.py
stactools/sentinel1/metadata_links.py
stactools/sentinel1/product_metadata.py
stactools/sentinel1/grd/__init__.py
stactools/sentinel1/grd/commands.py
stactools/sentinel1/grd/constants.py
stactools/sentinel1/grd/product_metadata.py
stactools/sentinel1/grd/properties.py
stactools/sentinel1/grd/stac.py
stactools/sentinel1/rtc/__init__.py
stactools/sentinel1/rtc/commands.py
stactools/sentinel1/rtc/constants.py
stactools/sentinel1/rtc/rtc_metadata.py
stactools/sentinel1/rtc/stac.py
stactools/sentinel1/slc/__init__.py
stactools/sentinel1/slc/commands.py
stactools/sentinel1/slc/constants.py
stactools/sentinel1/slc/metadata_links.py
stactools/sentinel1/slc/product_metadata.py
stactools/sentinel1/slc/properties.py
stactools/sentinel1/slc/stac.py
stactools_sentinel1-0.8.1.dist-info/licenses/LICENSE
stactools_sentinel1-0.8.1.dist-info/METADATA
stactools_sentinel1-0.8.1.dist-info/WHEEL
stactools_sentinel1-0.8.1.dist-info/top_level.txt
stactools_sentinel1-0.8.1.dist-info/RECORD
