Metadata-Version: 2.4
Name: stactools-sentinel1
Version: 0.8.1
Summary: stactools subpackage for creating sentinel1 STACs
Author-email: stac-utils <stac@radiant.earth>
Project-URL: Github, https://github.com/stactools-packages/sentinel1
Project-URL: Documentation, https://github.com/stactools-packages/sentinel1
Project-URL: Issues, https://github.com/stactools-packages/sentinel1/issues
Keywords: stactools,pystac,catalog,STAC,sentinel,GRD,radar
Classifier: Development Status :: 4 - Beta
Classifier: License :: OSI Approved :: Apache Software License
Classifier: Programming Language :: Python :: 3.9
Classifier: Programming Language :: Python :: 3.10
Classifier: Programming Language :: Python :: 3.11
Classifier: Programming Language :: Python :: 3.12
Classifier: Programming Language :: Python :: 3.13
Requires-Python: >=3.9
License-File: LICENSE
Requires-Dist: stactools>=0.4.5
Requires-Dist: pystac~=1.9.0
Dynamic: license-file
